{"name":"mnml","folder":"electro\/mnml","recursive":"0","description":"","color":"#1F3B66","no_shuffle":"0","hot_rotation":{"enable":"0","song_num":"20","at_beginning":"1","shuffle_beginning":"1","song_age_days":"2000","insert_multiplier":"4"},"spot":{"folder":"station","every_nth_song":"2","offset":"1","shuffle_beginning":"1","order":"shuffle","order_by":""},"podcast":{"folder":"...","every_nth_song":"","offset":"","cast_num":"","random_first":""},"file_name":"6a38a22ddf66d9074e153ea2e058e185","intro":{"folder":"station","random":"1"},"timestamp":"1455879496","slug":"mnml"}